manimlib_pptx/__init__.py
manimlib_pptx/pptxscene.py
manimlib_pptx/template.pptx
manimlib_pptx-0.1.0.dist-info/LICENSE
manimlib_pptx-0.1.0.dist-info/WHEEL
manimlib_pptx-0.1.0.dist-info/METADATA
manimlib_pptx-0.1.0.dist-info/RECORD
