Metadata-Version: 2.1
Name: manimlib-pptx
Version: 0.1.0
Summary: 
Author: RythenGlyth
Author-email: rythenglyth@gmail.com
Requires-Python: >=3.8,<4.0
Classifier: Programming Language :: Python :: 3
Classifier: Programming Language :: Python :: 3.10
Classifier: Programming Language :: Python :: 3.8
Classifier: Programming Language :: Python :: 3.9
Requires-Dist: lxml
Requires-Dist: manimgl
Requires-Dist: python-pptx
